semantic_link_sempy-0.12.2.dist-info/licenses/LICENSE.txt
sempy/__init__.py
sempy/_version.py
sempy/dotnet.runtime.config.json
sempy/_metadata/__init__.py
sempy/_metadata/_mdataframe.py
sempy/_metadata/_meta_utils.py
sempy/_metadata/_mseries.py
sempy/_utils/__init__.py
sempy/_utils/_dotnet.py
sempy/_utils/_graph.py
sempy/_utils/_icons.py
sempy/_utils/_log.py
sempy/_utils/_ordered_set.py
sempy/_utils/_pandas_utils.py
sempy/_utils/_telemetry.py
sempy/dependencies/__init__.py
sempy/dependencies/_find.py
sempy/dependencies/_plot.py
sempy/dependencies/_stats.py
sempy/dependencies/_validate.py
sempy/fabric/__init__.py
sempy/fabric/_cache.py
sempy/fabric/_credentials.py
sempy/fabric/_datacategory.py
sempy/fabric/_daxmagics.py
sempy/fabric/_environment.py
sempy/fabric/_flat.py
sempy/fabric/_flat_list_annotations.py
sempy/fabric/_flat_list_apps.py
sempy/fabric/_flat_list_calculation_items.py
sempy/fabric/_flat_list_columns.py
sempy/fabric/_flat_list_dataflows.py
sempy/fabric/_flat_list_datasources.py
sempy/fabric/_flat_list_gateways.py
sempy/fabric/_flat_list_hierarchies.py
sempy/fabric/_flat_list_partitions.py
sempy/fabric/_flat_list_perspectives.py
sempy/fabric/_flat_list_relationships.py
sempy/fabric/_keyvault.py
sempy/fabric/_metadatakeys.py
sempy/fabric/_token_provider.py
sempy/fabric/_utils.py
sempy/fabric/_vertipaq.py
sempy/fabric/_bpa/__init__.py
sempy/fabric/_bpa/_bpa.py
sempy/fabric/_bpa/_rules.py
sempy/fabric/_bpa/_types/__init__.py
sempy/fabric/_client/__init__.py
sempy/fabric/_client/_adomd_connection.py
sempy/fabric/_client/_base_dataset_client.py
sempy/fabric/_client/_cognitiveservice_rest_api.py
sempy/fabric/_client/_connection_mode.py
sempy/fabric/_client/_dataset_onelake_import.py
sempy/fabric/_client/_dataset_rest_client.py
sempy/fabric/_client/_dataset_xmla_client.py
sempy/fabric/_client/_fabric_rest_api.py
sempy/fabric/_client/_languages.py
sempy/fabric/_client/_pbi_rest_api.py
sempy/fabric/_client/_refresh_execution_details.py
sempy/fabric/_client/_rest_client.py
sempy/fabric/_client/_rest_client_async.py
semantic_link_sempy-0.12.2.dist-info/METADATA
semantic_link_sempy-0.12.2.dist-info/WHEEL
semantic_link_sempy-0.12.2.dist-info/top_level.txt
semantic_link_sempy-0.12.2.dist-info/RECORD
