Metadata-Version: 2.4
Name: semantic-link-sempy
Version: 0.12.2
Summary: Semantic link for Microsoft Fabric
Home-page: https://learn.microsoft.com/en-us/fabric/data-science/semantic-link-overview
Author: Microsoft
Author-email: semanticdatascience@service.microsoft.com
License: proprietary and confidential
Platform: Microsoft Fabric
Classifier: Development Status :: 4 - Beta
Classifier: Intended Audience :: Developers
Classifier: License :: Other/Proprietary License
Classifier: Programming Language :: Python :: 3.10
Requires-Python: >=3.10
License-File: LICENSE.txt
Requires-Dist: clr_loader>=0.2.5
Requires-Dist: fabric-analytics-sdk[online-notebook]==0.0.1
Requires-Dist: graphviz>=0.20.1
Requires-Dist: azure-storage-blob>=12.18.3
Requires-Dist: azure-core>=1.29.4
Requires-Dist: azure-keyvault-secrets>=4.7.0
Requires-Dist: azure-storage-file-datalake>=12.12.0
Requires-Dist: pyarrow>=12.0.1
Requires-Dist: pythonnet>=3.0.1
Requires-Dist: scikit_learn>=1.2.2
Requires-Dist: setuptools>=68.2.2
Requires-Dist: tqdm>=4.65.0
Requires-Dist: rich>=13.3.5
Requires-Dist: regex>=2023.8.8
Requires-Dist: pandas>=1.5.3
Requires-Dist: pyjwt>=2.4.0
Requires-Dist: pyspark>=3.4.1
Requires-Dist: requests>=2.31.0
Requires-Dist: aiohttp>=3.8.6
Requires-Dist: IPython>=8.14.0
Requires-Dist: tenacity>=8.2.3
Dynamic: author
Dynamic: author-email
Dynamic: classifier
Dynamic: description
Dynamic: description-content-type
Dynamic: home-page
Dynamic: license
Dynamic: license-file
Dynamic: platform
Dynamic: requires-dist
Dynamic: requires-python
Dynamic: summary
